cartup-dag/__init__.py
cartup-dag/airflow/__init__.py
cartup-dag/airflow/airflow_service.py
cartup-dag/build/__init__.py
cartup-dag/build/lib/__init__.py
cartup-dag/build/lib/airflow/__init__.py
cartup-dag/build/lib/airflow/airflow_service.py
cartup-dag/build/lib/config/__init__.py
cartup-dag/build/lib/config/config.py
cartup-dag/build/lib/config/config_local.py
cartup-dag/build/lib/config/config_prod.py
cartup-dag/build/lib/server/__init__.py
cartup-dag/build/lib/server/response_ws.py
cartup-dag/build/lib/server/server.py
cartup-dag/build/lib/ssh/__init__.py
cartup-dag/build/lib/ssh/ssh_client.py
cartup-dag/build/lib/utils/__init__.py
cartup-dag/build/lib/utils/utils.py
cartup-dag/config/__init__.py
cartup-dag/config/config.py
cartup-dag/config/config_local.py
cartup-dag/config/config_prod.py
cartup-dag/jobs/__init__.py
cartup-dag/jobs/dashboard/__init__.py
cartup-dag/jobs/dashboard/dags/__init__.py
cartup-dag/jobs/dashboard/dags/dag_dashboard.py
cartup-dag/jobs/search/__init__.py
cartup-dag/jobs/search/dags/__init__.py
cartup-dag/jobs/search/dags/dag_search.py
cartup-dag/server/__init__.py
cartup-dag/server/response_ws.py
cartup-dag/server/server.py
cartup-dag/ssh/__init__.py
cartup-dag/ssh/ssh_client.py
cartup-dag/utils/__init__.py
cartup-dag/utils/utils.py
cartup_dag/__init__.py
cartup_dag/airflow/__init__.py
cartup_dag/airflow/airflow_service.py
cartup_dag/build/__init__.py
cartup_dag/config/__init__.py
cartup_dag/config/config.py
cartup_dag/config/config_local.py
cartup_dag/config/config_notification.py
cartup_dag/config/config_prod.py
cartup_dag/jobs/__init__.py
cartup_dag/jobs/dashboard/__init__.py
cartup_dag/jobs/dashboard/dags/__init__.py
cartup_dag/jobs/dashboard/dags/dag_dashboard.py
cartup_dag/jobs/search/__init__.py
cartup_dag/jobs/search/dags/__init__.py
cartup_dag/jobs/search/dags/dag_search.py
cartup_dag/server/__init__.py
cartup_dag/server/response_ws.py
cartup_dag/server/server.py
cartup_dag/server/test.py
cartup_dag/ssh/__init__.py
cartup_dag-1.0.4.dist-info/METADATA
cartup_dag-1.0.4.dist-info/WHEEL
cartup_dag-1.0.4.dist-info/top_level.txt
cartup_dag-1.0.4.dist-info/RECORD
