Metadata-Version: 2.1
Name: cartup-dag
Version: 1.0.4
Summary: DAG Job Library.
Author: Arvind Rapaka
Author-email: arvind@cartup.ai
License: Apache
Classifier: Intended Audience :: Developers
Classifier: Programming Language :: Python
Classifier: License :: OSI Approved :: Apache Software License
Classifier: Programming Language :: Python :: 3 :: Only
Classifier: Programming Language :: Python :: 3.7
Classifier: Programming Language :: Python :: 3.8
Classifier: Programming Language :: Python :: 3.9
Requires-Dist: email-validator (==1.3.1)
Requires-Dist: exceptiongroup (==1.1.2)
Requires-Dist: filelock (==3.12.2)
Requires-Dist: Flask (==2.2.5)
Requires-Dist: Flask-AppBuilder (==4.3.1)
Requires-Dist: Flask-Babel (==2.0.0)
Requires-Dist: Flask-Caching (==2.0.2)
Requires-Dist: Flask-JWT-Extended (==4.5.2)
Requires-Dist: Flask-Limiter (==3.3.1)
Requires-Dist: Flask-Login (==0.6.2)
Requires-Dist: Flask-Session (==0.5.0)
Requires-Dist: Flask-SQLAlchemy (==2.5.1)
Requires-Dist: Flask-WTF (==1.1.1)
Requires-Dist: unicodecsv (==0.14.1)
Requires-Dist: Werkzeug (==2.2.3)
Requires-Dist: boto3 (==1.28.11)
Requires-Dist: botocore (==1.31.11)
